{
  "generatedAt": "2026-06-20T00:20:09.877Z",
  "items": [
    {
      "id": 1,
      "title": "Node.js揭露與修補12個漏洞，當中涵蓋兩個高風險漏洞",
      "link": "https://www.ithome.com.tw/news/176743",
      "publishedAt": "2026-06-20 01:06:32",
      "summary": "開放原始碼JavaScript執行環境Node.js這幾天發布安全性更新公告，揭露與修補12個漏洞（CVSS評分尚未公布），其中兩個為高風險漏洞，6個為中風險漏洞，4個為低風險漏洞，Node.js 22、Node.js 24、Node.js 26均受到影響，目前開發團隊已釋出修補漏洞的更新版本——Node.js 22.23.0、Node.js 24.17.0、Node.js 26.3.1。",
      "source": "iThome",
      "tag": "繁中"
    },
    {
      "id": 2,
      "title": "fix(test): guard benchmark qa cli args",
      "link": "https://github.com/openclaw/openclaw/commit/56c040501817708a457a64224cb470ecb514068c",
      "publishedAt": "2026-06-20T00:13:13Z",
      "summary": "fix(test): guard benchmark qa cli args",
      "source": "OpenClaw Commits",
      "tag": "OpenClaw",
      "titleZh": "OpenClaw 程式碼更新：修正(test): guard benchmark qa cli args",
      "summaryZh": "重點：修正(test): guard benchmark qa cli args..."
    },
    {
      "id": 3,
      "title": "fix(macos): create DMG output directories (#95133)",
      "link": "https://github.com/openclaw/openclaw/commit/b6d754e3cb62a3c5b5855c08b1a43ac98b67ca4e",
      "publishedAt": "2026-06-20T00:11:23Z",
      "summary": "fix(macos): create DMG output directories (#95133)",
      "source": "OpenClaw Commits",
      "tag": "OpenClaw",
      "titleZh": "OpenClaw 程式碼更新：修正(macos): create DMG output directories (#95133)",
      "summaryZh": "重點：修正(macos): create DMG output directories (#95133)..."
    },
    {
      "id": 4,
      "title": "refactor(qa): share parity comparison helpers",
      "link": "https://github.com/openclaw/openclaw/commit/6e732b306338f95d53386f378cbe8bc367121b34",
      "publishedAt": "2026-06-20T00:09:38Z",
      "summary": "refactor(qa): share parity comparison helpers",
      "source": "OpenClaw Commits",
      "tag": "OpenClaw",
      "titleZh": "OpenClaw 程式碼更新：refactor(qa): share parity comparison helpers",
      "summaryZh": "重點：refactor(qa): share parity comparison helpers..."
    },
    {
      "id": 5,
      "title": "fix(test): clean release check cli errors",
      "link": "https://github.com/openclaw/openclaw/commit/423b1b3a426a283c98a6d84ee11e60eac71ace55",
      "publishedAt": "2026-06-20T00:08:16Z",
      "summary": "fix(test): clean release check cli errors",
      "source": "OpenClaw Commits",
      "tag": "OpenClaw",
      "titleZh": "OpenClaw 程式碼更新：修正(test): clean 版本發布 check cli errors",
      "summaryZh": "重點：修正(test): clean 版本發布 check cli errors..."
    },
    {
      "id": 6,
      "title": "衛福部清單還沒出，經濟部搶發補助！240 億「國藥國造」遭批路徑不明",
      "link": "https://technews.tw/2026/06/20/strategic-drug-localization-program/",
      "publishedAt": "Sat, 20 Jun 2026 00:00:19 +0000",
      "summary": "政府推動 50 到 60 項關鍵藥物國產化，啟動 240 億元藥物韌性整備計畫，試圖降低對全球供應鏈依賴。然而 [&#8230;]",
      "source": "TechNews",
      "tag": "繁中"
    },
    {
      "id": 7,
      "title": "朱諾號重大發現：直擊木星前震區，揭開百年宇宙射線起源之謎",
      "link": "https://technews.tw/2026/06/20/jupiter-bow-shock-accelerates-electrons-to-near-light-speed/",
      "publishedAt": "Fri, 19 Jun 2026 16:00:16 +0000",
      "summary": "美國國家航空暨太空總署（NASA）的朱諾號（Juno）探測器最新觀測結果顯示，木星周圍的弓形震波（bow sh [&#8230;]",
      "source": "TechNews",
      "tag": "繁中"
    },
    {
      "id": 8,
      "title": "研究：生理痛選錯止痛藥，超市數據揭女性購藥盲點",
      "link": "https://technews.tw/2026/06/20/why-you-might-not-be-buying-the-right-pain-relief-for-period-cramps/",
      "publishedAt": "Fri, 19 Jun 2026 16:00:10 +0000",
      "summary": "一項分析英國大型超市交易紀錄的研究指出，許多女性在生理期腹痛時，可能買到的不是最合適的止痛藥。研究團隊檢視英格 [&#8230;]",
      "source": "TechNews",
      "tag": "繁中"
    },
    {
      "id": 9,
      "title": "史丹佛科學家打造體外子宮，助攻不孕醫學研究",
      "link": "https://technews.tw/2026/06/20/stanford-scientists-create-artificial-uterus-advance-infertility-research/",
      "publishedAt": "Fri, 19 Jun 2026 16:00:01 +0000",
      "summary": "許多接受試管嬰兒治療的不孕夫妻最感挫折的是，醫師明明培養出健康胚胎，卻還是無法成功懷孕。其實胚胎植入子宮後的「 [&#8230;]",
      "source": "TechNews",
      "tag": "繁中"
    },
    {
      "id": 10,
      "title": "蘋果在巴西開放第三方App市集與外部付款",
      "link": "https://www.ithome.com.tw/news/176737",
      "publishedAt": "2026-06-19 10:06:13",
      "summary": "蘋果週四（6/18）宣布，根據與巴西競爭監管機關CADE（Conselho Administrativo de Defesa Econômica）所達成的協議，自iOS 26.5起開放開發者透過第三方應用程式商店散布App，並允許在App Store上架的應用程式導入Apple In-App Purchase以外的付款方式。這是蘋果繼歐盟《數位市場法》（DMA）後，再度因監管要求調整iOS生態系規則。",
      "source": "iThome",
      "tag": "繁中"
    }
  ]
}