{
  "generatedAt": "2026-05-02T10:54:00.400Z",
  "items": [
    {
      "id": 1,
      "title": "fix: drop stale service PATH entries (#75440) (thanks @leonaIee)",
      "link": "https://github.com/openclaw/openclaw/commit/7edac014e5e79ab047c6511ca5ea996edc899ace",
      "publishedAt": "2026-05-02T10:50:50Z",
      "summary": "fix: drop stale service PATH entries (#75440) (thanks @leonaIee)",
      "source": "OpenClaw Commits",
      "tag": "OpenClaw",
      "titleZh": "OpenClaw 程式碼更新：修正: drop stale service PATH entries (#75440) (thanks @leonaIee)",
      "summaryZh": "重點：修正: drop stale service PATH entries (#75440) (thanks @leonaIee)..."
    },
    {
      "id": 2,
      "title": "refactor(daemon): reuse shared path normalizer",
      "link": "https://github.com/openclaw/openclaw/commit/626a22decb9b21f0db024a23588db9e6634692f8",
      "publishedAt": "2026-05-02T10:50:50Z",
      "summary": "refactor(daemon): reuse shared path normalizer",
      "source": "OpenClaw Commits",
      "tag": "OpenClaw",
      "titleZh": "OpenClaw 程式碼更新：refactor(daemon): reuse shared path normalizer",
      "summaryZh": "重點：refactor(daemon): reuse shared path normalizer..."
    },
    {
      "id": 3,
      "title": "docs: add service path changelog",
      "link": "https://github.com/openclaw/openclaw/commit/0d747536de1d6840b589ba2f71c557b39db6fea6",
      "publishedAt": "2026-05-02T10:50:50Z",
      "summary": "docs: add service path changelog",
      "source": "OpenClaw Commits",
      "tag": "OpenClaw",
      "titleZh": "OpenClaw 文件更新：文件: add service path changelog",
      "summaryZh": "重點：文件: add service path changelog..."
    },
    {
      "id": 4,
      "title": "fix: drop stale service PATH entries",
      "link": "https://github.com/openclaw/openclaw/commit/49b1b084448be49708383e9bab8e32ea95b17442",
      "publishedAt": "2026-05-02T10:50:50Z",
      "summary": "fix: drop stale service PATH entries",
      "source": "OpenClaw Commits",
      "tag": "OpenClaw",
      "titleZh": "OpenClaw 程式碼更新：修正: drop stale service PATH entries",
      "summaryZh": "重點：修正: drop stale service PATH entries..."
    },
    {
      "id": 5,
      "title": "獨家 OLED 面板供應、記憶體短缺推升成本，iPhone 20 價格看漲",
      "link": "https://technews.tw/2026/05/02/samsung-display-tipped-to-win-exclusive-iphone-20-oled-deal/",
      "publishedAt": "Sat, 02 May 2026 09:24:35 +0000",
      "summary": "蘋果傳在 2027 年 iPhone 20 改採前所未有的全新設計，搭載四曲面螢幕，結合蘋果的 Liquid [&#8230;]",
      "source": "TechNews",
      "tag": "繁中"
    },
    {
      "id": 6,
      "title": "記憶體短缺衝擊！蘋果下架 Mac mini 256GB 版本，售價改為 799 美元起跳",
      "link": "https://technews.tw/2026/05/02/apple-stops-selling-mac-mini-with-256gb-of-storage/",
      "publishedAt": "Sat, 02 May 2026 07:04:04 +0000",
      "summary": "外媒 MacRumors 在美注意到，Mac mini 建議售價現在變為 799 美元起跳，蘋果已自線上 Ap [&#8230;]",
      "source": "TechNews",
      "tag": "繁中"
    },
    {
      "id": 7,
      "title": "美國發現大型鋰礦夠用 328 年，可生產 1.3 億台車與 5 千億支手機",
      "link": "https://finance.technews.tw/2026/05/02/lithium-in-eastern-states-could-replace-imports-for-a-century-or-more/",
      "publishedAt": "Sat, 02 May 2026 07:00:48 +0000",
      "summary": "美國地質調查局（USGS）4 月 28 日公布最新研究，確認阿帕拉契山脈（Appalachian Mounta [&#8230;]",
      "source": "TechNews",
      "tag": "繁中"
    },
    {
      "id": 8,
      "title": "聯發科：余振華擔任非全職顧問，未來將持續投資台積電先進封裝",
      "link": "https://finance.technews.tw/2026/05/02/mediatek-yu-zhenhua-serves-as-a-part-time-advisor-and-will-continue-to-invest-in-tsmcs-advanced-packaging/",
      "publishedAt": "Sat, 02 May 2026 06:00:59 +0000",
      "summary": "針對近期市場傳出前台積電研發副總經理、素有 「台積電研發六騎士」 之稱的先進封裝研發大將余振華，在結束長達 3 [&#8230;]",
      "source": "TechNews",
      "tag": "繁中"
    },
    {
      "id": 9,
      "title": "「SBTI」爆紅背後的真相，中國年輕人為何寧可當「廢物」也不願再聽成功學",
      "link": "https://technews.tw/2026/05/02/sbti-2/",
      "publishedAt": "Sat, 02 May 2026 06:00:40 +0000",
      "summary": "「你的 SBTI 是什麼？」就在今年春天的某個深夜，這句話悄悄變成了熱門社交暗號。消息發酵不到 24 小時，相 [&#8230;]",
      "source": "TechNews",
      "tag": "繁中"
    },
    {
      "id": 10,
      "title": "IBM Bob報到！專為企業設計與培養的軟體開發人員",
      "link": "https://technews.tw/2026/05/02/ibm-bob/",
      "publishedAt": "Sat, 02 May 2026 06:00:07 +0000",
      "summary": "IBM 宣布在全球推出 IBM Bob — 專為企業「培養」的軟體開發數位員工。Bob 不僅能協助軟體開發團隊 [&#8230;]",
      "source": "TechNews",
      "tag": "繁中"
    }
  ]
}