{
  "generatedAt": "2026-06-17T21:07:56.655Z",
  "items": [
    {
      "id": 1,
      "title": "chore: add claw-score skill (#94263)",
      "link": "https://github.com/openclaw/openclaw/commit/846591b5542787fda15be56e97d63fbff94cff75",
      "publishedAt": "2026-06-17T21:03:35Z",
      "summary": "chore: add claw-score skill (#94263) Co-authored-by: Kevin Lin",
      "source": "OpenClaw Commits",
      "tag": "OpenClaw",
      "titleZh": "OpenClaw 程式碼更新：chore: add claw-score skill (#94263)",
      "summaryZh": "重點：chore: add claw-score skill (#94263) Co-authored-by: Kevin Lin..."
    },
    {
      "id": 2,
      "title": "fix(test): kill openclaw test process groups",
      "link": "https://github.com/openclaw/openclaw/commit/912946ff941597f797e146cab8cbffd093152737",
      "publishedAt": "2026-06-17T20:58:03Z",
      "summary": "fix(test): kill openclaw test process groups",
      "source": "OpenClaw Commits",
      "tag": "OpenClaw",
      "titleZh": "OpenClaw 程式碼更新：修正(test): kill OpenClaw test process groups",
      "summaryZh": "重點：修正(test): kill OpenClaw test process groups..."
    },
    {
      "id": 3,
      "title": "test(scripts): wait for mock stderr flush",
      "link": "https://github.com/openclaw/openclaw/commit/5893758957833529549523316607f5cb3a55e4ea",
      "publishedAt": "2026-06-17T20:55:29Z",
      "summary": "test(scripts): wait for mock stderr flush",
      "source": "OpenClaw Commits",
      "tag": "OpenClaw",
      "titleZh": "OpenClaw 程式碼更新：test(scripts): wait for mock stderr flush",
      "summaryZh": "重點：test(scripts): wait for mock stderr flush..."
    },
    {
      "id": 4,
      "title": "feat(codex): support remote app-server plugins (#94203)",
      "link": "https://github.com/openclaw/openclaw/commit/bc5081c587308a4d2ea2697cd23a3b0e96e662f5",
      "publishedAt": "2026-06-17T20:52:34Z",
      "summary": "feat(codex): support remote app-server plugins (#94203) * feat(codex): support remote app-server plugins * fix(codex): refresh remote plugin apps after install * fix(codex): infer remote app-server topology * docs(codex): document remote app-server plugin config * fix(codex): remove remote mutation policy * fix(codex): simplify remote workspace root * docs(codex): fix remote app-server PR docs",
      "source": "OpenClaw Commits",
      "tag": "OpenClaw",
      "titleZh": "OpenClaw 程式碼更新：新功能(codex): support remote app-server plugins (#94203)",
      "summaryZh": "重點：新功能(codex): support remote app-server plugins (#94203) * 新功能(codex): support remote app-server plugins * 修正(codex): refr..."
    },
    {
      "id": 5,
      "title": "FIFA平臺後端漏洞能讓駭客免費播放世界盃賽事、置換影像、修改比分",
      "link": "https://www.ithome.com.tw/news/176691",
      "publishedAt": "2026-06-17 12:06:49",
      "summary": "一名研究人員發現國際足球協會（FIFA）後端平臺API漏洞，使其得以劫持足球世界盃轉播攝影機及賽事影像，或是變更賽事比分等紀錄。FIFA在接獲通報後已修補漏洞。 名為BobDaHacker的研究人員指出，漏洞出在FIFA後臺的身分與授權機制設計錯誤，使未經授權的人員得以登入內部系統，存取賽事串流影像管理介面。",
      "source": "iThome",
      "tag": "繁中"
    },
    {
      "id": 6,
      "title": "惡意瀏覽器擴充套件竊取AI對話內容再現新案例，近9萬名用戶受影響",
      "link": "https://www.ithome.com.tw/news/176689",
      "publishedAt": "2026-06-17 12:06:21",
      "summary": "當使用者與生成式AI的互動，逐漸成為生活與工作流程不可或缺的一部分，AI對話內容也成為攻擊者覬覦的資料來源。上週我們報導過，資安公司G Data揭露部分Chrome擴充套件會監控與收集使用者與AI的對話，近日資安研究專案MalExt Sentry又揭露另一起類似案例，偽裝為廣告攔截工具的惡意瀏覽器擴充套件，會攔截與收集使用者與生成式AI服務的互動內容。",
      "source": "iThome",
      "tag": "繁中"
    },
    {
      "id": 7,
      "title": "中國駭客Earth Lusca打造惡意軟體SprySOCKS變種，於政府機關從事攻擊活動",
      "link": "https://www.ithome.com.tw/news/176684",
      "publishedAt": "2026-06-17 12:06:02",
      "summary": "一般而言，Windows作業系統是駭客主要的攻擊目標，他們會專門為該平臺打造惡意程式，後續為擴大攻擊範圍，再移植、開發Linux與macOS平臺版本，不過最近有駭客組織反其道而行，製作Linux惡意程式的Windows變種，來從事攻擊活動。",
      "source": "iThome",
      "tag": "繁中"
    },
    {
      "id": 8,
      "title": "都柏林大學將主導歐盟6G安全專案，開發6G原生網路威脅情資平臺",
      "link": "https://www.ithome.com.tw/news/176678",
      "publishedAt": "2026-06-17 11:06:45",
      "summary": "愛爾蘭都柏林大學（University College Dublin，UCD）在6月11日宣布，將主導歐盟Horizon Europe架構下、智慧網路與服務聯合事業（Smart Networks and Services Joint Undertaking，SNS JU）支持的SHIELD-6G專案，總經費達800萬歐元。這項專案將集結19個國際合作夥伴，目標是開發面向6G網路的AI驅動威脅情資平臺。",
      "source": "iThome",
      "tag": "繁中"
    },
    {
      "id": 9,
      "title": "Google發布ChromeOS長期支援版更新，修補17項記憶體相關重大漏洞",
      "link": "https://www.ithome.com.tw/news/176680",
      "publishedAt": "2026-06-17 11:06:38",
      "summary": "ChromeOS作業系統長期支援版LTS-144的更新版144.0.7559.255於6月13日上線，並修補40項漏洞，當中分別有17項漏洞被評為有重大風險，22項有高風險，1項有中度風險。",
      "source": "iThome",
      "tag": "繁中"
    },
    {
      "id": 10,
      "title": "AWS推出PQC就緒度掃描工具，檢視TLS端點抗量子準備狀態",
      "link": "https://www.ithome.com.tw/news/176682",
      "publishedAt": "2026-06-17 11:06:23",
      "summary": "為了因應量子運算即將造成大規模既有加密機制保護力不足的危機，IT產業近期密切關注後量子密碼學（Post-Quantum Cryptography，PQC）的導入與遷移議題，公有雲業者AWS在上個月宣布推出後量子密碼學就緒度掃描工具PQC Readiness Scanner，這是以AWS Config合規套件建置的解決方案。",
      "source": "iThome",
      "tag": "繁中"
    }
  ]
}