{
  "generatedAt": "2026-07-14T02:34:02.003Z",
  "items": [
    {
      "id": 1,
      "title": "新型攻擊GhostCommit將提示注入指令藏進圖片，誘使AI代理外洩機密",
      "link": "https://www.ithome.com.tw/news/177271",
      "publishedAt": "2026-07-14 07:07:10",
      "summary": "資安研究組織ASSET Research Group公開名為GhostCommit的概念驗證攻擊，顯示攻擊者可將提示注入指令藏在PNG圖片中，避開只檢查文字差異的AI程式碼審查工具。惡意內容合併至儲存庫後，具備影像理解能力的程式開發代理可能在後續工作中讀取圖片，依照其中指示開啟環境變數設定檔.env，再將檔案內容逐位元組轉為整數序列寫入程式碼。",
      "source": "iThome",
      "tag": "繁中"
    },
    {
      "id": 2,
      "title": "refactor(runtime): remove redundant provider aliases (#107013)",
      "link": "https://github.com/openclaw/openclaw/commit/6a5736baa5afe54a2bd156ee7b28a47128a2bb72",
      "publishedAt": "2026-07-14T02:33:23Z",
      "summary": "refactor(runtime): remove redundant provider aliases (#107013)",
      "source": "OpenClaw Commits",
      "tag": "OpenClaw",
      "titleZh": "OpenClaw 程式碼更新：refactor(runtime): remove redundant provider aliases (#107013)",
      "summaryZh": "重點：refactor(runtime): remove redundant provider aliases (#107013)..."
    },
    {
      "id": 3,
      "title": "refactor(ai): remove unused websocket debug stats",
      "link": "https://github.com/openclaw/openclaw/commit/241d6dec7881d0243a89aa7bb3b383bd072d8863",
      "publishedAt": "2026-07-14T02:33:03Z",
      "summary": "refactor(ai): remove unused websocket debug stats",
      "source": "OpenClaw Commits",
      "tag": "OpenClaw",
      "titleZh": "OpenClaw 程式碼更新：refactor(ai): remove unused websocket debug stats",
      "summaryZh": "重點：refactor(ai): remove unused websocket debug stats..."
    },
    {
      "id": 4,
      "title": "refactor(qa-lab): trim dead export surface (#107016)",
      "link": "https://github.com/openclaw/openclaw/commit/44fcbc612d0e9d74a6c01ed25ff36e7c67f39191",
      "publishedAt": "2026-07-14T02:32:13Z",
      "summary": "refactor(qa-lab): trim dead export surface (#107016) * refactor(qa-lab): narrow report and config exports * refactor(qa-lab): keep live test seams private * refactor(qa-lab): remove dead runtime wrappers * chore(deadcode): refresh QA Lab export baseline",
      "source": "OpenClaw Commits",
      "tag": "OpenClaw",
      "titleZh": "OpenClaw 程式碼更新：refactor(qa-lab): trim dead export surface (#107016)",
      "summaryZh": "重點：refactor(qa-lab): trim dead export surface (#107016) * refactor(qa-lab): narrow report and config exports * refactor(qa-..."
    },
    {
      "id": 5,
      "title": "fix(cli): restore plugin authoring LOC ratchet (#107003)",
      "link": "https://github.com/openclaw/openclaw/commit/a93330bf999815ac451073e6f1167fedb75e75c5",
      "publishedAt": "2026-07-14T02:31:55Z",
      "summary": "fix(cli): restore plugin authoring LOC ratchet (#107003)",
      "source": "OpenClaw Commits",
      "tag": "OpenClaw",
      "titleZh": "OpenClaw 程式碼更新：修正(cli): restore plugin authoring LOC ratchet (#107003)",
      "summaryZh": "重點：修正(cli): restore plugin authoring LOC ratchet (#107003)..."
    },
    {
      "id": 6,
      "title": "聯電矽光子布局進入新里程，攜手 SILITH 完成首批量產矽光子晶圓交付",
      "link": "https://finance.technews.tw/2026/07/14/umc-and-silith-complete-the-first-batch-of-mass-produced-silicon-photonic-wafers-delivery/",
      "publishedAt": "Tue, 14 Jul 2026 02:30:12 +0000",
      "summary": "聯電與SILITH共同宣布，聯電新加坡晶圓廠完成首批量產矽光子晶圓交付，象徵雙方合作邁入量產新里程碑，並進一步 [&#8230;]",
      "source": "TechNews",
      "tag": "繁中"
    },
    {
      "id": 7,
      "title": "SK 海力士 ADR 大溢價、恐續跌？美韓股連動漸深",
      "link": "https://finance.technews.tw/2026/07/14/geopolitical-shock-exposes-sk-hynix-leverage-after-hot-adr-debut/",
      "publishedAt": "Tue, 14 Jul 2026 02:30:03 +0000",
      "summary": "SK 海力士（SK Hynix）的美國存託憑證（ADR）上週五（7 月 10 日）剛在那斯達克股票交易所（Na [&#8230;]",
      "source": "TechNews",
      "tag": "繁中"
    },
    {
      "id": 8,
      "title": "記憶體供應趨緊，調研：Q226 全球智慧手機出貨年減 11%",
      "link": "https://finance.technews.tw/2026/07/14/q226-global-smartphone-shipment/",
      "publishedAt": "Tue, 14 Jul 2026 02:29:58 +0000",
      "summary": "據調研機構 Counterpoint Research《智慧型手機市場監測》初步統計，2026 年第二季全球智 [&#8230;]",
      "source": "TechNews",
      "tag": "繁中"
    },
    {
      "id": 9,
      "title": "蘋果創高 分析師看好秋季新品發表會再添動能",
      "link": "https://finance.technews.tw/2026/07/14/apple-record-high-analysts-bullish-fall-product-launch-momentum/",
      "publishedAt": "Tue, 14 Jul 2026 02:20:08 +0000",
      "summary": "近來大盤震盪，但蘋果（Apple Inc.）股價默默創新高，分析人士也看好，隨著蘋果擴大市占率並推出新的 AI [&#8230;]",
      "source": "TechNews",
      "tag": "繁中"
    },
    {
      "id": 10,
      "title": "台積電法說倒數！外資齊喊買、最高衝上 3,800 元，價格重點一次看",
      "link": "https://technews.tw/2026/07/14/foreign-investors-see-tsmc-2026-q2-and-capex/",
      "publishedAt": "Tue, 14 Jul 2026 02:14:40 +0000",
      "summary": "隨著台積電法說會將於週四（16 日）登場，多間外資和法人已經發布最新報告，並調高目標價，價格介於 2,888 [&#8230;]",
      "source": "TechNews",
      "tag": "繁中"
    }
  ]
}